pyvirtuals/__init__.py
pyvirtuals-0.1.dist-info/LICENSE
pyvirtuals-0.1.dist-info/METADATA
pyvirtuals-0.1.dist-info/WHEEL
pyvirtuals-0.1.dist-info/top_level.txt
pyvirtuals-0.1.dist-info/RECORD
